LICENSE.txt
README.md
setup.cfg
setup.py
webapp_builder/__init__.py
webapp_builder/main.py
webapp_builder/utilities.py
webapp_builder.egg-info/PKG-INFO
webapp_builder.egg-info/SOURCES.txt
webapp_builder.egg-info/dependency_links.txt
webapp_builder.egg-info/requires.txt
webapp_builder.egg-info/top_level.txt