Metadata-Version: 2.1
Name: webapp-builder
Version: 1.0.0
Summary: Webapp Builder -- LLM/LVM Code Generator
Home-page: https://github.com/george-mountain/web-app-builder--LLM
Author: George Mountain
Author-email: engrmountain@gmail.com
License: MIT
Download-URL: https://github.com/george-mountain/web-app-builder--LLM/archive/refs/tags/1.0.0.tar.gz
Project-URL: Bug Tracker, https://github.com/george-mountain/web-app-builder--LLM/issues
Keywords: pypi,llm,lvm,large language model,large vision model,code generator,web app builder,AI
Platform: UNKNOWN
Classifier: Development Status :: 3 - Alpha
Classifier: Intended Audience :: Developers
Classifier: License :: OSI Approved :: MIT License
Classifier: Programming Language :: Python :: 3
Classifier: Programming Language :: Python :: 3.8
Classifier: Programming Language :: Python :: 3.9
Classifier: Programming Language :: Python :: 3.10
Classifier: Programming Language :: Python :: 3.11
License-File: LICENSE.txt
